hyperdict/__init__.py
hyperdict/hyperdict.py
hyperdict-1.0.0.dist-info/LICENSE
hyperdict-1.0.0.dist-info/WHEEL
hyperdict-1.0.0.dist-info/METADATA
hyperdict-1.0.0.dist-info/RECORD
