Metadata-Version: 2.1
Name: hyperdict
Version: 1.0.0
Summary: Python dictionaries, but on steroids.
Home-page: https://github.com/j0fiN/hyperdict
License: Apache 2.0
Keywords: dictionaries,utility,one liners,hyper,dict
Author: Jofin
Author-email: jofinfab@gmail.com
Requires-Python: >=3.6,<4.0
Classifier: License :: Other/Proprietary License
Classifier: Programming Language :: Python :: 3
Classifier: Programming Language :: Python :: 3.6
Classifier: Programming Language :: Python :: 3.7
Classifier: Programming Language :: Python :: 3.8
Classifier: Programming Language :: Python :: 3.9
Requires-Dist: executing (>=0.6.0,<0.7.0)
Project-URL: Repository, https://github.com/j0fiN/hyperdict
